yfh_tools/__init__.py
yfh_tools/db.py
yfh_tools/proxy.py
yfh_tools-0.0.1.dist-info/METADATA
yfh_tools-0.0.1.dist-info/WHEEL
yfh_tools-0.0.1.dist-info/top_level.txt
yfh_tools-0.0.1.dist-info/RECORD
