Metadata-Version: 2.1
Name: yfh-tools
Version: 0.0.1
Summary: date series data synchronization
Author: feihan ye
Author-email: 445280206@qq.com
Classifier: Programming Language :: Python :: 3
Classifier: License :: OSI Approved :: MIT License
Classifier: Operating System :: OS Independent
